LICENSE
MANIFEST.in
README.rst
setup.py
ask/__init__.py
ask.egg-info/PKG-INFO
ask.egg-info/SOURCES.txt
ask.egg-info/dependency_links.txt
ask.egg-info/not-zip-safe
ask.egg-info/top_level.txt