Metadata-Version: 1.0
Name: ask
Version: 0.0.4
Summary: Easy input validation for python
Home-page: https://github.com/chive/ask
Author: Kim Thoenen
Author-email: kim@smuzey.ch
License: MIT
Platform: OS Independent
